Workbook

Sheet LEEME
A1: MIGAL · Catálogo sintético CRM
A2: Personas, empresas, marcas, DNI/RUC, teléfonos, obras y direcciones creados para el caso. Son ficticios y no deben usarse para contactar, facturar o repartir.
A4: Concepto | B4: Uso en este workbook
A5: [E] | B5: Evidencia respaldada por levantamiento o fuente del negocio.
A6: [I] | B6: Interpretación razonada a partir de evidencia.
A7: [S] | B7: Supuesto provisional pendiente de validación.
A8: [ND] | B8: No determinado: no existe información suficiente.
A9: AS-IS | B9: Cómo funciona actualmente MIGAL.
A10: TO-BE | B10: Mejora propuesta por el equipo.
A11: [SIM] | B11: Datos ficticios con apariencia realista; los números no están verificados como documentos válidos.
A12: Alcance | B12: Cuenta, contacto, canal/fuente, interacción, oportunidad y cotización antes del pedido confirmado.
A13: Fuera de alcance | B13: Contrato técnico CRM–ERP, ejecución del pedido, reserva de inventario, entrega, factura, pago y posventa.
A14: Referencia docente | B14: Distritos de Lima usados como contexto. Nombres, calles, numeración, predios y empresas son ficticios; no son direcciones verificadas.

Sheet Resumen
A1: Resumen del caso sintético CRM de MIGAL
A2: Indicadores calculados a partir de las hojas del workbook.
A4: Indicador | B4: Valor | C4: Interpretación
A5: Clientes sintéticos | B5: =COUNTA(Clientes!A5:A100) | C5: Cuentas usadas únicamente para ejemplificar el modelo CRM.
A6: Contactos sintéticos | B6: =COUNTA(Contactos!A5:A100) | C6: Dueños, maestros, receptores y clientes asociados a cuentas.
A7: Oportunidades | B7: =COUNTA(Oportunidades!A5:A100) | C7: Intereses comerciales con seguimiento.
A8: Cotizaciones/versiones | B8: =COUNTA(Cotizaciones!A5:A100) | C8: Versiones emitidas para las oportunidades.
A9: Oportunidades abiertas | B9: =COUNTIF(Oportunidades!L5:L100,"Abierta") | C9: Aún requieren seguimiento.
A10: Ganadas totales | B10: =COUNTIF(Oportunidades!L5:L100,"Ganada total") | C10: Compra adjudicada completamente a MIGAL.
A11: Ganadas parciales | B11: =COUNTIF(Oportunidades!L5:L100,"Ganada parcial") | C11: Parte de la compra se realiza en MIGAL y otra parte no.
A12: Perdidas | B12: =COUNTIF(Oportunidades!L5:L100,"Perdida") | C12: No se concreta compra asociada a la oportunidad.

Sheet Clientes
A1: Clientes / cuentas sintéticas
A4: id_cliente | B4: nombre_razon_social | C4: tipo_cliente | D4: documento_identidad | E4: estado_relacion | F4: responsable_comercial | G4: origen_principal | H4: nota
A5: CLI-SIM-001 | B5: Rosa Elena Huamán Salcedo | C5: Obra | D5: 73481629 | E5: Activa | F5: Propietaria | G5: Referido maestro | H5: SIM · Ampliación del tercer piso; coordina con maestro Luis Salcedo.
A6: CLI-SIM-002 | B6: Julio César Rojas Cárdenas | C6: Obra | D6: 68251947 | E6: Activa | F6: Dueño | G6: WhatsApp | H6: SIM · Columnas y techo de vivienda; compra cemento y compara fierro.
A7: CLI-SIM-003 | B7: Patricia Milagros Quispe Vega | C7: Obra | D7: 48162473 | E7: Activa | F7: Propietaria | G7: Referido maestro | H7: SIM · Instalaciones sanitarias y segunda etapa de vivienda familiar.
A8: CLI-SIM-004 | B8: Carmen Alicia Paredes Rivas | C8: Particular | D8: 59148326 | E8: Activa | F8: Dueño | G8: Presencial | H8: SIM · Reparación de sala y dormitorio; recoge compras pequeñas en tienda.
A9: CLI-SIM-005 | B9: Luis Alberto Mendoza Huerta | C9: Particular | D9: 72053618 | E9: Activa | F9: Propietaria | G9: WhatsApp | H9: SIM · Pintado de fachada; solicita propuesta por WhatsApp.
A10: CLI-SIM-006 | B10: Obras y Acabados Ladera Norte S.A.C. | C10: Empresa | D10: 20987461352 | E10: Activa | F10: Propietaria | G10: Referido | H10: SIM · Empresa ficticia de remodelación; requiere factura por materiales.
A11: CLI-SIM-007 | B11: Héctor Manuel Cárdenas Soto | C11: Obra | D11: 48573041 | E11: Activa | F11: Dueño | G11: Teléfono | H11: SIM · Vivienda en Puente Piedra; consulta ladrillo por millar y agregados.
A12: CLI-SIM-008 | B12: María Teresa Salazar Ponce | C12: Particular | D12: 64921837 | E12: Inactiva | F12: Propietaria | G12: Presencial | H12: SIM · Cliente sin obra activa; última consulta por mantenimiento doméstico.
A13: CLI-SIM-009 | B13: Ana Lucía Torres Medina | C13: Obra | D13: 47836415 | E13: Activa | F13: Propietaria | G13: WhatsApp | H13: SIM · Autoconstrucción en Carabayllo; evalúa cantidades y costo de traslado.
A14: CLI-SIM-010 | B14: Instalaciones Hidráulicas Valle Claro E.I.R.L. | C14: Empresa | D14: 20691374825 | E14: Activa | F14: Dueño | G14: WhatsApp | H14: SIM · Contratista ficticio; renovación de tuberías y tanque en local de SMP.
A15: CLI-SIM-011 | B15: José Antonio Villanueva Ramos | C15: Particular | D15: 45783296 | E15: Activa | F15: Dueño | G15: Presencial | H15: SIM · Compra de mostrador; pide lista para reparar muebles y fijaciones.
A16: CLI-SIM-012 | B16: Edgar Raúl Espinoza Carranza | C16: Obra | D16: 48294651 | E16: Activa | F16: Propietaria | G16: Referido maestro | H16: SIM · Ampliación de vivienda en Ancón; solicitó condición de crédito.

Sheet Contactos
A1: Contactos sintéticos vinculados a las cuentas
A4: id_contacto | B4: id_cliente | C4: nombre_contacto | D4: rol_contacto | E4: telefono | F4: canal_preferido | G4: uso_operativo | H4: consentimiento_promocional | I4: estado | J4: nota
A5: CON-SIM-001 | B5: CLI-SIM-001 | C5: Rosa Elena Huamán Salcedo | D5: Dueño de obra | E5: 900100101 | F5: WhatsApp | G5: Sí | H5: No determinado | I5: Activo | J5: SIM · Propietaria; confirma presupuesto del tercer piso.
A6: CON-SIM-002 | B6: CLI-SIM-001 | C6: Luis Fernando Salcedo Poma | D6: Maestro de obra | E6: 900100118 | F6: WhatsApp | G6: Sí | H6: No determinado | I6: Activo | J6: SIM · Maestro albañil; prepara metrado y coordina descarga.
A7: CON-SIM-003 | B7: CLI-SIM-002 | C7: Julio César Rojas Cárdenas | D7: Dueño de obra | E7: 900100135 | F7: Teléfono | G7: Sí | H7: No determinado | I7: Activo | J7: SIM · Propietario; negocia cemento y acero para columnas.
A8: CON-SIM-004 | B8: CLI-SIM-002 | C8: Víctor Hugo Palomino Chacón | D8: Maestro de obra | E8: 900100152 | F8: WhatsApp | G8: Sí | H8: No determinado | I8: Activo | J8: SIM · Maestro de obra; revisa medidas del acero y cantidades.
A9: CON-SIM-005 | B9: CLI-SIM-003 | C9: Miguel Ángel Yupanqui Ríos | D9: Maestro de obra | E9: 900100169 | F9: WhatsApp | G9: Sí | H9: No determinado | I9: Activo | J9: SIM · Gasfitero; remite diámetros y accesorios faltantes.
A10: CON-SIM-006 | B10: CLI-SIM-003 | C10: Patricia Milagros Quispe Vega | D10: Dueño de obra | E10: 900100186 | F10: WhatsApp | G10: Sí | H10: No determinado | I10: Activo | J10: SIM · Propietaria; decide flete y compra de agregados.
A11: CON-SIM-007 | B11: CLI-SIM-004 | C11: Carmen Alicia Paredes Rivas | D11: Cliente | E11: 900100203 | F11: Presencial | G11: Sí | H11: No determinado | I11: Activo | J11: SIM · Compra para reparación interior; atención en mostrador.
A12: CON-SIM-008 | B12: CLI-SIM-005 | C12: Luis Alberto Mendoza Huerta | D12: Cliente | E12: 900100220 | F12: WhatsApp | G12: Sí | H12: No determinado | I12: Activo | J12: SIM · Coordina color y rendimiento de pintura.
A13: CON-SIM-009 | B13: CLI-SIM-006 | C13: Mariela Beatriz Córdova Peña | D13: Representante | E13: 900100237 | F13: WhatsApp | G13: Sí | H13: No determinado | I13: Activo | J13: SIM · Encargada de compras de Ladera Norte; solicita factura.
A14: CON-SIM-010 | B14: CLI-SIM-007 | C14: Juan Carlos Huerta Chávez | D14: Maestro de obra | E14: 900100254 | F14: Teléfono | G14: Sí | H14: No determinado | I14: Activo | J14: SIM · Maestro albañil; espera confirmación del lote de ladrillos.
A15: CON-SIM-011 | B15: CLI-SIM-009 | C15: Ana Lucía Torres Medina | D15: Dueño de obra | E15: 900100271 | F15: WhatsApp | G15: Sí | H15: No determinado | I15: Activo | J15: SIM · Propietaria de obra; decide distribución de compras.
... A20: CON-SIM-016 | B20: CLI-SIM-012 | C20: Edgar Raúl Espinoza Carranza | D20: Dueño de obra | E20: 900100356 | F20: WhatsApp | G20: Sí | H20: No determinado | I20: Activo | J20: SIM · Propietario; consulta pago fraccionado para ampliación.

Sheet Direcciones_Obra
A1: Direcciones / obras sintéticas
A4: id_direccion | B4: id_cliente | C4: nombre_obra | D4: direccion_ubicacion | E4: distrito | F4: indicaciones | G4: estado | H4: fuente_direccion | I4: nota
A5: DIR-SIM-001 | B5: CLI-SIM-001 | C5: Ampliación tercer piso — familia Huamán | D5: Jr. Los Alhelíes 318, Urb. Naranjal | E5: San Martín de Porres | F5: Portón verde; descargar en vereda lateral. Acceso a tercer piso por escalera exterior. | G5: Activa | H5: WhatsApp | I5: SIM · Numeración y predio ficticios.
A6: DIR-SIM-002 | B6: CLI-SIM-002 | C6: Techo y columnas — vivienda Rojas | D6: Calle Las Retamas 246, Urb. San Diego | E6: San Martín de Porres | F6: Coordinar con Víctor Palomino; frente angosto, descargar por lotes. | G6: Activa | H6: Ubicación compartida | I6: SIM · Numeración y predio ficticios.
A7: DIR-SIM-003 | B7: CLI-SIM-003 | C7: Remodelación sanitaria — vivienda Quispe | D7: Jr. Los Manzanos 527, Urb. Pro | E7: Los Olivos | F7: Puerta de fierro plomo; patio disponible para tuberías, agregados solo en exterior. | G7: Activa | H7: WhatsApp | I7: SIM · Numeración y predio ficticios.
A8: DIR-SIM-004 | B8: CLI-SIM-006 | C8: Acondicionamiento de consultorio — Ladera Norte | D8: Calle Las Dalias 164, Urb. Palao | E8: San Martín de Porres | F8: Ingreso por puerta lateral; proteger piso al trasladar materiales. | G8: Activa | H8: Texto | I8: SIM · Empresa, local y numeración ficticios.
A9: DIR-SIM-005 | B9: CLI-SIM-007 | C9: Primer piso — vivienda Cárdenas | D9: Mz. F Lt. 12, Asociación Los Jardines del Valle | E9: Puente Piedra | F9: Acceso por calle afirmada; confirmar condición de ingreso del camión antes de prometer fecha. | G9: Activa | H9: Llamada | I9: SIM · Asociación, lote y predio ficticios.
A10: DIR-SIM-006 | B10: CLI-SIM-009 | C10: Construcción vivienda — familia Torres | D10: Mz. K Lt. 8, Asociación Villa Los Cedros | E10: Carabayllo | F10: Consultar espacio de maniobra y descarga; maestro Óscar Rivas recibe materiales. | G10: Activa | H10: Ubicación compartida | I10: SIM · Asociación, lote y predio ficticios.
A11: DIR-SIM-007 | B11: CLI-SIM-010 | C11: Renovación de red de agua — Valle Claro | D11: Jr. Los Jazmines 683, Urb. Fiori | E11: San Martín de Porres | F11: Tanque ingresa por portón de 2.40 m; coordinar retiro de vehículo antes de descarga. | G11: Activa | H11: WhatsApp | I11: SIM · Empresa, local y numeración ficticios.
A12: DIR-SIM-008 | B12: CLI-SIM-012 | C12: Ampliación segundo piso — vivienda Espinoza | D12: Mz. D Lt. 21, Asociación Las Lomas del Pacífico | E12: Ancón | F12: Destino alejado; cotizar traslado por separado y confirmar acceso antes de ofrecer entrega. | G12: Activa | H12: WhatsApp | I12: SIM · Asociación, lote y predio ficticios.
A13: DIR-SIM-009 | B13: CLI-SIM-004 | C13: Reparación interior — vivienda Paredes | D13: Jr. Las Gardenias 156, Urb. Condevilla | E13: San Martín de Porres | F13: Compra pequeña; Carmen recoge brochas y discos en la tienda. | G13: Activa | H13: Presencial | I13: SIM · Numeración y predio ficticios.
A14: DIR-SIM-010 | B14: CLI-SIM-005 | C14: Pintado de fachada — vivienda Mendoza | D14: Calle Los Nísperos 208, Urb. Antares | E14: San Martín de Porres | F14: Fachada de dos niveles; confirmar color blanco antes de cerrar propuesta. | G14: Activa | H14: WhatsApp | I14: SIM · Numeración y predio ficticios.
A15: DIR-SIM-011 | B15: CLI-SIM-008 | C15: Mantenimiento de vivienda — Salazar | D15: Jr. Los Fresnos 375, Urb. Santa Luzmila | E15: Comas | F15: Sin trabajo activo; referencia conservada para consultas posteriores. | G15: Inactiva | H15: Presencial | I15: SIM · Numeración y predio ficticios.
A16: DIR-SIM-012 | B16: CLI-SIM-011 | C16: Reparaciones domésticas — Villanueva | D16: Calle Las Acacias 119, Urb. Los Jardines | E16: San Martín de Porres | F16: Retiro en tienda; no programar reparto para la consulta inicial. | G16: Activa | H16: Presencial | I16: SIM · Numeración y predio ficticios.

Sheet Productos_Referencia
A1: Productos de referencia sintéticos
A2: Las descripciones reflejan líneas reales del rubro; los códigos, marcas y precios usados en otros sheets son simulados.
A4: id_producto | B4: descripcion | C4: marca | D4: presentacion | E4: unidad_medida | F4: categoria | G4: estado | H4: nota
A5: PRD-SIM-001 | B5: Cemento Portland tipo I 42.5 kg | C5: Cementos Alto Valle | D5: Bolsa de 42.5 kg | E5: bolsa | F5: Cemento | G5: Activo | H5: SIM · Marca y ficha ficticias; no es catálogo comercial de MIGAL.
A6: PRD-SIM-002 | B6: Barra corrugada de acero 1/2 pulg x 9 m | C6: Aceros Forjanorte | D6: Varilla de 9 m | E6: unidad | F6: Fierro | G6: Activo | H6: SIM · Marca y ficha ficticias; no es catálogo comercial de MIGAL.
A7: PRD-SIM-003 | B7: Tubo PVC para agua fría 1/2 pulg x 5 m, clase 10 | C7: HidroNorte | D7: Tubo de 5 m | E7: unidad | F7: Gasfitería | G7: Activo | H7: SIM · Marca y ficha ficticias; no es catálogo comercial de MIGAL.
A8: PRD-SIM-004 | B8: Tubo PVC para desagüe 4 pulg x 3 m | C8: HidroNorte | D8: Tubo de 3 m | E8: unidad | F8: Gasfitería | G8: Activo | H8: SIM · Marca y ficha ficticias; no es catálogo comercial de MIGAL.
A9: PRD-SIM-005 | B9: Arena gruesa lavada para concreto | C9: Cantera Río Seco | D9: Venta por metro cúbico | E9: m3 | F9: Agregados | G9: Activo | H9: SIM · Marca y ficha ficticias; no es catálogo comercial de MIGAL.
A10: PRD-SIM-006 | B10: Arena fina para tarrajeo | C10: Cantera Río Seco | D10: Venta por metro cúbico | E10: m3 | F10: Agregados | G10: Activo | H10: SIM · Marca y ficha ficticias; no es catálogo comercial de MIGAL.
A11: PRD-SIM-007 | B11: Piedra chancada de 1/2 pulg | C11: Cantera Río Seco | D11: Venta por metro cúbico | E11: m3 | F11: Agregados | G11: Activo | H11: SIM · Marca y ficha ficticias; no es catálogo comercial de MIGAL.
A12: PRD-SIM-008 | B12: Ladrillo pandereta acanalado 9 x 12 x 23 cm | C12: Cerámicos Arcilla Norte | D12: Pieza de 9 x 12 x 23 cm | E12: unidad | F12: Albañilería | G12: Activo | H12: SIM · Marca y ficha ficticias; no es catálogo comercial de MIGAL.
A13: PRD-SIM-009 | B13: Ladrillo de techo hueco de 15 cm | C13: Cerámicos Arcilla Norte | D13: Pieza de 15 x 30 x 30 cm | E13: unidad | F13: Albañilería | G13: Activo | H13: SIM · Marca y ficha ficticias; no es catálogo comercial de MIGAL.
A14: PRD-SIM-010 | B14: Cable de cobre TW 2.5 mm2 color rojo | C14: Conductores Voltacobre | D14: Rollo de 100 m | E14: rollo | F14: Eléctrico | G14: Activo | H14: SIM · Marca y ficha ficticias; no es catálogo comercial de MIGAL.
A15: PRD-SIM-011 | B15: Tomacorriente doble universal empotrable | C15: ElectroNexo | D15: Placa blanca, 16 A | E15: unidad | F15: Eléctrico | G15: Activo | H15: SIM · Marca y ficha ficticias; no es catálogo comercial de MIGAL.
... A24: PRD-SIM-020 | B24: Adhesivo PVC para tubería de agua | C24: HidroNorte | D24: Frasco de 250 mL | E24: unidad | F24: Gasfitería | G24: Activo | H24: SIM · Marca y ficha ficticias; no es catálogo comercial de MIGAL.

Sheet Oportunidades
A1: Oportunidades comerciales sintéticas
A4: id_oportunidad | B4: id_cliente | C4: id_contacto | D4: necesidad | E4: origen | F4: etapa | G4: probabilidad | H4: competencia_referencia | I4: proxima_accion | J4: fecha_proxima_accion | K4: responsable | L4: resultado | M4: motivo_no_adjudicacion | N4: nota
A5: OPP-SIM-001 | B5: CLI-SIM-001 | C5: CON-SIM-002 | D5: 100 bolsas de cemento, 40 barras de 1/2 pulg y 20 tubos de agua para tercer piso en Naranjal. | E5: Referido maestro | F5: Cotización | G5: Alta | H5: Sí | I5: Escribir a Rosa Huamán para confirmar revisión de COT-SIM-001-V01 con Luis Salcedo. | J5: 46312 | K5: Propietaria | L5: Abierta | N5: SIM · Historia comercial ficticia; no prueba venta, reserva, entrega ni pago.
A6: OPP-SIM-002 | B6: CLI-SIM-002 | C6: CON-SIM-004 | D6: 80 bolsas de cemento y 60 barras corrugadas para columnas de vivienda en San Diego. | E6: WhatsApp | F6: Cerrada | G6: Alta | H6: Sí | I6: Registrar cierre parcial: Julio Rojas adjudica cemento; el fierro queda con otra ferretería. | J6: 46312 | K6: Dueño | L6: Ganada parcial | M6: Fierro comprado a otra ferretería por menor precio; cemento adjudicado a MIGAL. | N6: SIM · Historia comercial ficticia; no prueba venta, reserva, entrega ni pago.
A7: OPP-SIM-003 | B7: CLI-SIM-003 | C7: CON-SIM-005 | D7: Cambiar red de agua y desagüe de dos baños; Miguel Yupanqui enviará medidas de la vivienda en Pro. | E7: Referido maestro | F7: Oportunidad | G7: Media | H7: No | I7: Pedir a Miguel Yupanqui metrado y diámetros de conexiones de ambos baños. | J7: 46313 | K7: Propietaria | L7: Abierta | N7: SIM · Historia comercial ficticia; no prueba venta, reserva, entrega ni pago.
A8: OPP-SIM-004 | B8: CLI-SIM-004 | C8: CON-SIM-007 | D8: 4 brochas de 3 pulg y 3 discos para reparar sala y dormitorio de vivienda en Condevilla. | E8: Presencial | F8: Cerrada | G8: Media | H8: No | I8: Archivar aceptación de Carmen Paredes; coordinar retiro de brochas y discos en mostrador. | J8: 46312 | K8: Dueño | L8: Ganada total | N8: SIM · Historia comercial ficticia; no prueba venta, reserva, entrega ni pago.
A9: OPP-SIM-005 | B9: CLI-SIM-005 | C9: CON-SIM-008 | D9: 5 galones de látex blanco y 6 brochas para fachada de dos niveles en Antares. | E9: WhatsApp | F9: Cerrada | G9: Media | H9: Sí | I9: Cerrar como perdida; Luis Mendoza eligió precio menor para pintura y brochas. | J9: 46313 | K9: Propietaria | L9: Perdida | M9: Cotización completa no adjudicada por precio de pintura y brochas. | N9: SIM · Historia comercial ficticia; no prueba venta, reserva, entrega ni pago.
A10: OPP-SIM-006 | B10: CLI-SIM-006 | C10: CON-SIM-009 | D10: 20 tubos PVC y 2 tanques de 1100 L para acondicionar consultorio en Palao. | E10: Referido | F10: Cerrada | G10: Alta | H10: No | I10: Conservar aceptación y condición de factura solicitada por Mariela Córdova. | J10: 46312 | K10: Propietaria | L10: Ganada total | N10: SIM · Historia comercial ficticia; no prueba venta, reserva, entrega ni pago.
A11: OPP-SIM-007 | B11: CLI-SIM-007 | C11: CON-SIM-010 | D11: 1200 ladrillos pandereta y 4 m3 de arena gruesa para muros en Puente Piedra. | E11: Teléfono | F11: Oportunidad | G11: Media | H11: No | I11: Llamar a Juan Huerta después de confirmar disponibilidad de ladrillo y acceso de descarga. | J11: 46312 | K11: Dueño | L11: Abierta | N11: SIM · Historia comercial ficticia; no prueba venta, reserva, entrega ni pago.
A12: OPP-SIM-008 | B12: CLI-SIM-009 | C12: CON-SIM-012 | D12: 150 bolsas de cemento y 100 barras de acero para vivienda familiar en Carabayllo. | E12: WhatsApp | F12: Cerrada | G12: Alta | H12: Sí | I12: Registrar compra parcial de Ana Torres; cemento adjudicado y fierro comprado a otro proveedor. | J12: 46312 | K12: Propietaria | L12: Ganada parcial | M12: Fierro comprado a otro proveedor; cemento adjudicado a MIGAL. | N12: SIM · Historia comercial ficticia; no prueba venta, reserva, entrega ni pago.
A13: OPP-SIM-009 | B13: CLI-SIM-010 | C13: CON-SIM-013 | D13: 1 tanque de 1100 L y 15 tubos de agua para renovar red de local en Fiori. | E13: WhatsApp | F13: Cerrada | G13: Alta | H13: No | I13: Conservar aceptación de Renato Gálvez y dejar coordinación de entrega para etapa operativa. | J13: 46313 | K13: Dueño | L13: Ganada total | N13: SIM · Historia comercial ficticia; no prueba venta, reserva, entrega ni pago.
A14: OPP-SIM-010 | B14: CLI-SIM-011 | C14: CON-SIM-014 | D14: Fijaciones y herramientas para muebles; José Villanueva aún debe precisar medidas y cantidades. | E14: Presencial | F14: Lead | G14: Baja | H14: No | I14: Solicitar a José Villanueva foto de tornillos y medida de fijaciones que necesita. | J14: 46315 | K14: Dueño | L14: Abierta | N14: SIM · Historia comercial ficticia; no prueba venta, reserva, entrega ni pago.
A15: OPP-SIM-011 | B15: CLI-SIM-012 | C15: CON-SIM-015 | D15: 200 bolsas de cemento y 120 barras para segundo piso en Ancón; cliente consulta crédito. | E15: Referido maestro | F15: Cerrada | G15: Alta | H15: Sí | I15: Cerrar como perdida; Edgar Espinoza no acepta pago al contado y no obtuvo crédito. | J15: 46313 | K15: Propietaria | L15: Perdida | M15: Cliente solicitó crédito para obra de Ancón; condición no autorizada. | N15: SIM · Historia comercial ficticia; no prueba venta, reserva, entrega ni pago.
A16: OPP-SIM-012 | B16: CLI-SIM-001 | C16: CON-SIM-001 | D16: Segunda etapa en Naranjal: Rosa Huamán solicita precio de cemento para vaciado de escalera. | E16: WhatsApp | F16: Oportunidad | G16: Media | H16: No | I16: Enviar a Rosa Huamán una propuesta separada cuando confirme bolsas para escalera. | J16: 46314 | K16: Propietaria | L16: Abierta | N16: SIM · Historia comercial ficticia; no prueba venta, reserva, entrega ni pago.
A17: OPP-SIM-013 | B17: CLI-SIM-003 | C17: CON-SIM-006 | D17: 100 bolsas de cemento y 5 m3 de arena para vivienda en Pro; compara flete de agregados. | E17: Teléfono | F17: Cerrada | G17: Alta | H17: Sí | I17: Registrar cierre parcial: Patricia Quispe acepta cemento y compra arena cerca de su obra. | J17: 46312 | K17: Dueño | L17: Ganada parcial | M17: Arena comprada cerca de la obra por costo de flete; cemento adjudicado. | N17: SIM · Historia comercial ficticia; no prueba venta, reserva, entrega ni pago.
A18: OPP-SIM-014 | B18: CLI-SIM-006 | C18: CON-SIM-009 | D18: Guantes talla L y herramientas para cuadrilla de Ladera Norte; Mariela enviará lista definitiva. | E18: WhatsApp | F18: Calificada | G18: Media | H18: No | I18: Pedir a Mariela Córdova cantidad de operarios y herramientas faltantes. | J18: 46314 | K18: Propietaria | L18: Abierta | N18: SIM · Historia comercial ficticia; no prueba venta, reserva, entrega ni pago.
A19: OPP-SIM-015 | B19: CLI-SIM-009 | C19: CON-SIM-011 | D19: 3 rollos de cable TW y 20 tomacorrientes para instalación eléctrica de vivienda en Carabayllo. | E19: WhatsApp | F19: Cerrada | G19: Media | H19: Sí | I19: Cerrar por falta de respuesta de Ana Torres tras seguimiento de la propuesta eléctrica. | J19: 46314 | K19: Propietaria | L19: Perdida | M19: Sin respuesta al seguimiento de cable y tomacorrientes. | N19: SIM · Historia comercial ficticia; no prueba venta, reserva, entrega ni pago.

Sheet Cotizaciones
A1: Cotizaciones y versiones sintéticas
A4: id_cotizacion | B4: numero_cotizacion | C4: version | D4: id_oportunidad | E4: id_direccion | F4: fecha_emision | G4: estado | H4: criterio_vigencia | I4: tipo_comprobante_previsto | J4: autorizador_excepcion | K4: motivo_excepcion | L4: nota
A5: COT-SIM-001-V01 | B5: COT-SIM-001 | C5: 1 | D5: OPP-SIM-001 | E5: DIR-SIM-001 | F5: 46311 | G5: En revisión | H5: Sujeta a actualización antes del pago si cambian costos | I5: Por definir | L5: SIM · Vivienda Huamán, Naranjal. Rosa revisa la lista con el maestro Luis Salcedo.
A6: COT-SIM-002-V01 | B6: COT-SIM-002 | C6: 1 | D6: OPP-SIM-002 | E6: DIR-SIM-002 | F6: 46311 | G6: Revisada | H6: Sujeta a actualización antes del pago si cambian costos | I6: Por definir | L6: SIM · Vivienda Rojas, San Diego. Oferta inicial sustituida por revisión de precio.
A7: COT-SIM-002-V02 | B7: COT-SIM-002 | C7: 2 | D7: OPP-SIM-002 | E7: DIR-SIM-002 | F7: 46311 | G7: Aceptada parcialmente | H7: Sujeta a actualización antes del pago si cambian costos | I7: Por definir | J7: Dueño | K7: Competencia | L7: SIM · Julio acepta cemento; fierro no adjudicado pese al ajuste a S/ 40.10.
A8: COT-SIM-004-V01 | B8: COT-SIM-004 | C8: 1 | D8: OPP-SIM-004 | E8: DIR-SIM-009 | F8: 46311 | G8: Aceptada | H8: Sujeta a actualización antes del pago si cambian costos | I8: Boleta | L8: SIM · Carmen acepta materiales para reparación; retiro en mostrador.
A9: COT-SIM-005-V01 | B9: COT-SIM-005 | C9: 1 | D9: OPP-SIM-005 | E9: DIR-SIM-010 | F9: 46311 | G9: No aceptada | H9: Sujeta a actualización antes del pago si cambian costos | I9: Boleta | L9: SIM · Luis Mendoza rechaza la oferta por una alternativa más económica.
A10: COT-SIM-006-V01 | B10: COT-SIM-006 | C10: 1 | D10: OPP-SIM-006 | E10: DIR-SIM-004 | F10: 46311 | G10: Aceptada | H10: Sujeta a actualización antes del pago si cambian costos | I10: Factura | L10: SIM · Ladera Norte solicita factura; aceptación comercial, sin ejecución operativa.
A11: COT-SIM-007-V01 | B11: COT-SIM-007 | C11: 1 | D11: OPP-SIM-007 | E11: DIR-SIM-005 | F11: 46311 | G11: En revisión | H11: Sujeta a actualización antes del pago si cambian costos | I11: Por definir | L11: SIM · Obra Cárdenas, Puente Piedra. Ladrillo y acceso a descarga por confirmar.
A12: COT-SIM-008-V01 | B12: COT-SIM-008 | C12: 1 | D12: OPP-SIM-008 | E12: DIR-SIM-006 | F12: 46311 | G12: Revisada | H12: Sujeta a actualización antes del pago si cambian costos | I12: Por definir | L12: SIM · Vivienda Torres, Carabayllo. Primera oferta, antes de negociar volumen.
A13: COT-SIM-008-V02 | B13: COT-SIM-008 | C13: 2 | D13: OPP-SIM-008 | E13: DIR-SIM-006 | F13: 46311 | G13: Aceptada parcialmente | H13: Sujeta a actualización antes del pago si cambian costos | I13: Por definir | J13: Propietaria | K13: Volumen | L13: SIM · Ana acepta cemento a S/ 30.80; fierro no adjudicado.
A14: COT-SIM-009-V01 | B14: COT-SIM-009 | C14: 1 | D14: OPP-SIM-009 | E14: DIR-SIM-007 | F14: 46311 | G14: Aceptada | H14: Sujeta a actualización antes del pago si cambian costos | I14: Factura | L14: SIM · Valle Claro acepta tanque y tubería; factura prevista, sin emisión fiscal.
A15: COT-SIM-011-V01 | B15: COT-SIM-011 | C15: 1 | D15: OPP-SIM-011 | E15: DIR-SIM-008 | F15: 46311 | G15: No aceptada | H15: Sujeta a actualización antes del pago si cambian costos | I15: Por definir | K15: Crédito no concedido | L15: SIM · Vivienda Espinoza, Ancón. No aceptada por condición de crédito.
A16: COT-SIM-013-V01 | B16: COT-SIM-013 | C16: 1 | D16: OPP-SIM-013 | E16: DIR-SIM-003 | F16: 46311 | G16: Revisada | H16: Sujeta a actualización antes del pago si cambian costos | I16: Por definir | L16: SIM · Vivienda Quispe, Pro. Primera propuesta de cemento y arena.
A17: COT-SIM-013-V02 | B17: COT-SIM-013 | C17: 2 | D17: OPP-SIM-013 | E17: DIR-SIM-003 | F17: 46311 | G17: Aceptada parcialmente | H17: Sujeta a actualización antes del pago si cambian costos | I17: Por definir | J17: Dueño | K17: Condición de entrega | L17: SIM · Patricia acepta cemento a S/ 30.90 y compra arena cerca por flete.
A18: COT-SIM-015-V01 | B18: COT-SIM-015 | C18: 1 | D18: OPP-SIM-015 | E18: DIR-SIM-006 | F18: 46311 | G18: No aceptada | H18: Sujeta a actualización antes del pago si cambian costos | I18: Por definir | L18: SIM · Instalación Torres, Carabayllo. No aceptada por ausencia de respuesta.

Sheet Cotizaciones_Detalle
A1: Detalle de cotizaciones sintéticas
A2: Los precios son completamente simulados y no deben utilizarse como lista real de MIGAL.
A4: id_cotizacion | B4: linea | C4: id_producto | D4: cantidad | E4: precio_referencia | F4: precio_ofrecido | G4: total_referencia | H4: total_ofrecido | I4: beneficio_cliente | J4: motivo_ajuste | K4: autorizado_por | L4: resultado_linea | M4: nota
A5: COT-SIM-001-V01 | B5: 1 | C5: PRD-SIM-001 | D5: 100 | E5: 31 | F5: 31 | G5: =D5*E5 | H5: =D5*F5 | I5: =G5-H5 | L5: Pendiente | M5: SIM · Precio y desenlace ficticios; importe de líneas, no total fiscal.
A6: COT-SIM-001-V01 | B6: 2 | C6: PRD-SIM-002 | D6: 40 | E6: 40.5 | F6: 40.5 | G6: =D6*E6 | H6: =D6*F6 | I6: =G6-H6 | L6: Pendiente | M6: SIM · Precio y desenlace ficticios; importe de líneas, no total fiscal.
A7: COT-SIM-001-V01 | B7: 3 | C7: PRD-SIM-003 | D7: 20 | E7: 20 | F7: 20 | G7: =D7*E7 | H7: =D7*F7 | I7: =G7-H7 | L7: Pendiente | M7: SIM · Precio y desenlace ficticios; importe de líneas, no total fiscal.
A8: COT-SIM-002-V01 | B8: 1 | C8: PRD-SIM-001 | D8: 80 | E8: 31.2 | F8: 31.2 | G8: =D8*E8 | H8: =D8*F8 | I8: =G8-H8 | L8: Adjudicada | M8: SIM · Precio y desenlace ficticios; importe de líneas, no total fiscal.
A9: COT-SIM-002-V01 | B9: 2 | C9: PRD-SIM-002 | D9: 60 | E9: 40.5 | F9: 40.5 | G9: =D9*E9 | H9: =D9*F9 | I9: =G9-H9 | L9: No adjudicada | M9: SIM · Precio y desenlace ficticios; importe de líneas, no total fiscal.
A10: COT-SIM-002-V02 | B10: 1 | C10: PRD-SIM-001 | D10: 80 | E10: 31.2 | F10: 31 | G10: =D10*E10 | H10: =D10*F10 | I10: =G10-H10 | J10: Volumen | K10: Dueño | L10: Adjudicada | M10: SIM · Precio y desenlace ficticios; importe de líneas, no total fiscal.
A11: COT-SIM-002-V02 | B11: 2 | C11: PRD-SIM-002 | D11: 60 | E11: 40.5 | F11: 40.1 | G11: =D11*E11 | H11: =D11*F11 | I11: =G11-H11 | J11: Competencia | K11: Dueño | L11: No adjudicada | M11: SIM · Precio y desenlace ficticios; importe de líneas, no total fiscal.
A12: COT-SIM-004-V01 | B12: 1 | C12: PRD-SIM-013 | D12: 4 | E12: 12 | F12: 12 | G12: =D12*E12 | H12: =D12*F12 | I12: =G12-H12 | L12: Adjudicada | M12: SIM · Precio y desenlace ficticios; importe de líneas, no total fiscal.
A13: COT-SIM-004-V01 | B13: 2 | C13: PRD-SIM-014 | D13: 3 | E13: 8.5 | F13: 8.5 | G13: =D13*E13 | H13: =D13*F13 | I13: =G13-H13 | L13: Adjudicada | M13: SIM · Precio y desenlace ficticios; importe de líneas, no total fiscal.
A14: COT-SIM-005-V01 | B14: 1 | C14: PRD-SIM-012 | D14: 5 | E14: 55 | F14: 55 | G14: =D14*E14 | H14: =D14*F14 | I14: =G14-H14 | L14: No adjudicada | M14: SIM · Precio y desenlace ficticios; importe de líneas, no total fiscal.
A15: COT-SIM-005-V01 | B15: 2 | C15: PRD-SIM-013 | D15: 6 | E15: 12 | F15: 11.8 | G15: =D15*E15 | H15: =D15*F15 | I15: =G15-H15 | J15: Competencia | K15: Propietaria | L15: No adjudicada | M15: SIM · Precio y desenlace ficticios; importe de líneas, no total fiscal.
A16: COT-SIM-006-V01 | B16: 1 | C16: PRD-SIM-003 | D16: 20 | E16: 20.5 | F16: 20.5 | G16: =D16*E16 | H16: =D16*F16 | I16: =G16-H16 | L16: Adjudicada | M16: SIM · Precio y desenlace ficticios; importe de líneas, no total fiscal.
A17: COT-SIM-006-V01 | B17: 2 | C17: PRD-SIM-019 | D17: 2 | E17: 480 | F17: 480 | G17: =D17*E17 | H17: =D17*F17 | I17: =G17-H17 | L17: Adjudicada | M17: SIM · Precio y desenlace ficticios; importe de líneas, no total fiscal.
A18: COT-SIM-007-V01 | B18: 1 | C18: PRD-SIM-008 | D18: 1200 | E18: 1.2 | F18: 1.2 | G18: =D18*E18 | H18: =D18*F18 | I18: =G18-H18 | L18: Pendiente | M18: SIM · Precio y desenlace ficticios; importe de líneas, no total fiscal.
A19: COT-SIM-007-V01 | B19: 2 | C19: PRD-SIM-005 | D19: 4 | E19: 95 | F19: 95 | G19: =D19*E19 | H19: =D19*F19 | I19: =G19-H19 | L19: Pendiente | M19: SIM · Precio y desenlace ficticios; importe de líneas, no total fiscal.
A20: COT-SIM-008-V01 | B20: 1 | C20: PRD-SIM-001 | D20: 150 | E20: 31 | F20: 31 | G20: =D20*E20 | H20: =D20*F20 | I20: =G20-H20 | L20: Adjudicada | M20: SIM · Precio y desenlace ficticios; importe de líneas, no total fiscal.
A21: COT-SIM-008-V01 | B21: 2 | C21: PRD-SIM-002 | D21: 100 | E21: 40.5 | F21: 40.5 | G21: =D21*E21 | H21: =D21*F21 | I21: =G21-H21 | L21: No adjudicada | M21: SIM · Precio y desenlace ficticios; importe de líneas, no total fiscal.
A22: COT-SIM-008-V02 | B22: 1 | C22: PRD-SIM-001 | D22: 150 | E22: 31 | F22: 30.8 | G22: =D22*E22 | H22: =D22*F22 | I22: =G22-H22 | J22: Volumen | K22: Propietaria | L22: Adjudicada | M22: SIM · Precio y desenlace ficticios; importe de líneas, no total fiscal.
A23: COT-SIM-008-V02 | B23: 2 | C23: PRD-SIM-002 | D23: 100 | E23: 40.5 | F23: 40.4 | G23: =D23*E23 | H23: =D23*F23 | I23: =G23-H23 | J23: Competencia | K23: Propietaria | L23: No adjudicada | M23: SIM · Precio y desenlace ficticios; importe de líneas, no total fiscal.
A24: COT-SIM-009-V01 | B24: 1 | C24: PRD-SIM-019 | D24: 1 | E24: 480 | F24: 480 | G24: =D24*E24 | H24: =D24*F24 | I24: =G24-H24 | L24: Adjudicada | M24: SIM · Precio y desenlace ficticios; importe de líneas, no total fiscal.
A25: COT-SIM-009-V01 | B25: 2 | C25: PRD-SIM-003 | D25: 15 | E25: 20 | F25: 20 | G25: =D25*E25 | H25: =D25*F25 | I25: =G25-H25 | L25: Adjudicada | M25: SIM · Precio y desenlace ficticios; importe de líneas, no total fiscal.
A26: COT-SIM-011-V01 | B26: 1 | C26: PRD-SIM-001 | D26: 200 | E26: 30.8 | F26: 30.8 | G26: =D26*E26 | H26: =D26*F26 | I26: =G26-H26 | L26: No adjudicada | M26: SIM · Precio y desenlace ficticios; importe de líneas, no total fiscal.
A27: COT-SIM-011-V01 | B27: 2 | C27: PRD-SIM-002 | D27: 120 | E27: 40.4 | F27: 40.4 | G27: =D27*E27 | H27: =D27*F27 | I27: =G27-H27 | L27: No adjudicada | M27: SIM · Precio y desenlace ficticios; importe de líneas, no total fiscal.
A28: COT-SIM-013-V01 | B28: 1 | C28: PRD-SIM-001 | D28: 100 | E28: 31.1 | F28: 31.1 | G28: =D28*E28 | H28: =D28*F28 | I28: =G28-H28 | L28: Adjudicada | M28: SIM · Precio y desenlace ficticios; importe de líneas, no total fiscal.
A29: COT-SIM-013-V01 | B29: 2 | C29: PRD-SIM-005 | D29: 5 | E29: 96 | F29: 96 | G29: =D29*E29 | H29: =D29*F29 | I29: =G29-H29 | L29: No adjudicada | M29: SIM · Precio y desenlace ficticios; importe de líneas, no total fiscal.
A30: COT-SIM-013-V02 | B30: 1 | C30: PRD-SIM-001 | D30: 100 | E30: 31.1 | F30: 30.9 | G30: =D30*E30 | H30: =D30*F30 | I30: =G30-H30 | J30: Condición de entrega | K30: Dueño | L30: Adjudicada | M30: SIM · Precio y desenlace ficticios; importe de líneas, no total fiscal.
A31: COT-SIM-013-V02 | B31: 2 | C31: PRD-SIM-005 | D31: 5 | E31: 96 | F31: 96 | G31: =D31*E31 | H31: =D31*F31 | I31: =G31-H31 | L31: No adjudicada | M31: SIM · Arena no adjudicada por flete; precio sin ajuste.
A32: COT-SIM-015-V01 | B32: 1 | C32: PRD-SIM-010 | D32: 3 | E32: 150 | F32: 150 | G32: =D32*E32 | H32: =D32*F32 | I32: =G32-H32 | L32: No adjudicada | M32: SIM · Precio y desenlace ficticios; importe de líneas, no total fiscal.
A33: COT-SIM-015-V01 | B33: 2 | C33: PRD-SIM-011 | D33: 20 | E33: 18 | F33: 18 | G33: =D33*E33 | H33: =D33*F33 | I33: =G33-H33 | L33: No adjudicada | M33: SIM · Precio y desenlace ficticios; importe de líneas, no total fiscal.

Sheet Decisiones_Comerciales
A1: Decisiones comerciales sintéticas
A4: id_decision | B4: tipo_decision | C4: id_oportunidad | D4: id_cotizacion | E4: objeto_afectado | F4: situacion | G4: decision | H4: decidido_por | I4: fecha_decision | J4: evidencia_esperada | K4: clasificacion | L4: nota
A5: DEC-SIM-001 | B5: Descuento | C5: OPP-SIM-002 | D5: COT-SIM-002-V02 | E5: PRD-SIM-002 | F5: Julio Rojas informa que otra ferretería mejora el precio del fierro para San Diego. | G5: Ajuste a S/ 40.10 por barra autorizado; cliente finalmente compra fierro fuera. | H5: Dueño | I5: 46311 | J5: COT-SIM-002-V02; referencia S/ 40.50; ofrecido S/ 40.10; motivo y autorizador. | K5: TO-BE/SIM | L5: SIM · Decisión ficticia para exposición; no validada por MIGAL.
A6: DEC-SIM-002 | B6: Descuento | C6: OPP-SIM-008 | D6: COT-SIM-008-V02 | E6: PRD-SIM-001 | F6: Ana Torres solicita mejorar precio por 150 bolsas para vivienda en Carabayllo. | G6: Precio de cemento S/ 30.80 autorizado; cliente adjudica esa línea. | H6: Propietaria | I6: 46311 | J6: COT-SIM-008-V02; 150 bolsas; diferencia S/ 30.00; autorización por volumen. | K6: TO-BE/SIM | L6: SIM · Decisión ficticia para exposición; no validada por MIGAL.
A7: DEC-SIM-003 | B7: Promesa | C7: OPP-SIM-007 | D7: COT-SIM-007-V01 | E7: PRD-SIM-008 | F7: Juan Huerta pide fecha para 1200 ladrillos; aún falta confirmar lote y acceso en Puente Piedra. | G7: Fecha de entrega pendiente de disponibilidad y revisión de acceso. | H7: Dueño | I7: 46311 | J7: COT-SIM-007-V01; 1200 piezas; consulta a proveedor; responsable de respuesta. | K7: TO-BE/SIM | L7: SIM · Decisión ficticia para exposición; no validada por MIGAL.
A8: DEC-SIM-004 | B8: Promesa | C8: OPP-SIM-009 | D8: COT-SIM-009-V01 | E8: Tanque 1100 L y tubería | F8: Renato Gálvez confirma portón y espacio para descarga en el local de Fiori. | G8: Promesa condicionada a confirmar jornada, vehículo y personal; no hay reserva ni entrega ejecutada. | H8: Dueño | I8: 46311 | J8: COT-SIM-009-V01; DIR-SIM-007; condición comunicada y responsable. | K8: TO-BE/SIM | L8: SIM · Decisión ficticia para exposición; no validada por MIGAL.
A9: DEC-SIM-005 | B9: Facturación | C9: OPP-SIM-006 | D9: COT-SIM-006-V01 | E9: Comprobante previsto | F9: Mariela Córdova solicita factura para Obras y Acabados Ladera Norte S.A.C. | G9: Factura prevista; identificación fiscal ficticia en ficha. No emitida. | H9: Propietaria | I9: 46311 | J9: COT-SIM-006-V01; cuenta CLI-SIM-006; condición fiscal registrada. | K9: TO-BE/SIM | L9: SIM · Decisión ficticia para exposición; no validada por MIGAL.
A10: DEC-SIM-006 | B10: Facturación | C10: OPP-SIM-004 | D10: COT-SIM-004-V01 | E10: Comprobante previsto | F10: Carmen Paredes pide boleta por brochas y discos para reparación de vivienda. | G10: Boleta prevista; retiro en tienda por coordinar. No emitida. | H10: Dueño | I10: 46311 | J10: COT-SIM-004-V01; cuenta CLI-SIM-004; condición comercial. | K10: TO-BE/SIM | L10: SIM · Decisión ficticia para exposición; no validada por MIGAL.

Sheet Trazabilidad_Fuentes
A1: Trazabilidad de afirmaciones y fuentes
A4: id_fuente | B4: tipo | C4: fuente | D4: fecha | E4: afirmacion_respaldada | F4: uso_en_workbook | G4: observacion
A5: FN-01 | B5: Negocio | C5: Monografía 1 - Grupo 1 - SI704V | D5: 2026-10-15 | E5: Operación, actores, canales, precios, cotizaciones, reparto, responsabilidades | F5: Base AS-IS | G5: Documento interno elaborado por el equipo
A6: FN-02 | B6: Negocio | C6: Aclaraciones de campo registradas por Brenda | D6: 2026-10-16 | E6: Contactos, obras, competencia, descuentos, seguimiento, facturación, direcciones e infraestructura | F6: Base AS-IS | G6: Levantamiento complementario
A7: FC-01 | B7: Docente | C7: GE703 Sesión 6 - CRM, marketing y ventas | D7: 2026-10 | E7: Cuenta, contacto, oportunidad, cotización y frontera conceptual CRM–ERP | F7: Marco conceptual | G7: No aporta datos reales de MIGAL
A8: FC-02 | B8: Docente | C8: GE703 Instrucciones y rúbrica del curso | D8: 2026-10-15 | E8: Alcance del entregable comercial | F8: Delimitación de alcance | G8: Corte antes del pedido confirmado
A9: FD-01 | B9: Docente | C9: Catálogos GE703 S6 / Modelo CRM_ERP Maestro | D9: 2026-10 | E9: Objetos y atributos de referencia | F9: Inspiración estructural | G9: Los valores del caso Andina son sintéticos
A10: FS-01 | B10: Simulación | C10: Caso ficticio elaborado para el proyecto MIGAL | D10: 2026-10-16 | E10: Nombres, DNI/RUC, teléfonos, obras, direcciones, marcas, especificaciones, precios e historias comerciales. | F10: Datos SIM del libro | G10: Creación sintética; no es levantamiento de clientes ni fuente de precios reales.

Sheet Catalogos_Apoyo
A1: Catálogos de apoyo propuestos
A4: catalogo | B4: valor | C4: uso | D4: clasificacion
A5: Probabilidad | B5: Baja | C5: Oportunidades | D5: TO-BE
A6: Probabilidad | B6: Media | C6: Oportunidades | D6: TO-BE
A7: Probabilidad | B7: Alta | C7: Oportunidades | D7: TO-BE
A8: Resultado | B8: Abierta | C8: Oportunidades | D8: TO-BE
A9: Resultado | B9: Ganada total | C9: Oportunidades | D9: TO-BE
A10: Resultado | B10: Ganada parcial | C10: Oportunidades | D10: I + TO-BE
A11: Resultado | B11: Perdida | C11: Oportunidades | D11: TO-BE
A12: Motivo no adjudicación | B12: Precio de competencia | C12: Pérdida total/parcial | D12: TO-BE
A13: Motivo no adjudicación | B13: Falta de disponibilidad | C13: Pérdida total/parcial | D13: TO-BE
A14: Motivo no adjudicación | B14: Flete/entrega no conveniente | C14: Pérdida total/parcial | D14: TO-BE
A15: Motivo no adjudicación | B15: Crédito no concedido | C15: Pérdida total/parcial | D15: TO-BE
... A31: Comprobante previsto | B31: Por definir | C31: Condición comercial | D31: TO-BE
